{
  "collectionName": "components_assets_assets",
  "info": {
    "name": "Assets",
    "icon": "ad",
    "description": ""
  },
  "options": {},
  "attributes": {
    "image": {
      "model": "file",
      "via": "related",
      "allowedTypes": [
        "images"
      ],
      "plugin": "upload",
      "required": false,
      "pluginOptions": {}
    },
    "link": {
      "type": "string"
    },
    "placement": {
      "type": "enumeration",
      "enum": [
        "top",
        "center",
        "bottom"
      ]
    },
    "styleClass": {
      "type": "enumeration",
      "enum": [
        "shadow",
        "mockup"
      ]
    }
  }
}
